dotscript/__init__.py
dotscript/dot.py
dotscript/version.py
dotscript-1.1.0.dist-info/METADATA
dotscript-1.1.0.dist-info/WHEEL
dotscript-1.1.0.dist-info/top_level.txt
dotscript-1.1.0.dist-info/RECORD
